poutyne_transformers/__init__.py
poutyne_transformers/data.py
poutyne_transformers/loss.py
poutyne_transformers/metrics.py
poutyne_transformers/model.py
poutyne_transformers-0.1.0.4.1.dist-info/LICENSE
poutyne_transformers-0.1.0.4.1.dist-info/WHEEL
poutyne_transformers-0.1.0.4.1.dist-info/METADATA
poutyne_transformers-0.1.0.4.1.dist-info/RECORD
