Metadata-Version: 2.1
Name: poutyne-transformers
Version: 0.1.0.4.1
Summary: Train 🤗-transformers models with Poutyne.
Home-page: https://github.com/LennartKeller/poutyne-transformers
Author: Lennart Keller
Author-email: lennart.keller@googlemail.com
Requires-Python: >=3.9,<4.0
Classifier: Programming Language :: Python :: 3
Classifier: Programming Language :: Python :: 3.9
Requires-Dist: Poutyne (>=1.6,<2.0)
Requires-Dist: torch (>=1.9.0,<2.0.0)
Requires-Dist: transformers (>=4.11.3,<5.0.0)
Project-URL: Repository, https://github.com/LennartKeller/poutyne-transformers
